[
  {
    "id": 262,
    "title": "The da vinci code",
    "author": "Dan brown",
    "publish_date": "2000-10-08",
    "publisher": "Austral",
    "cover_state": "regular"
  },
  {
    "id": 529,
    "title": "My story",
    "author": "Me",
    "publish_date": "2018-05-05",
    "publisher": "Abc",
    "cover_state": "good"
  },
  {
    "id": 693,
    "title": "Moby dick",
    "author": "Unknow",
    "publish_date": "1840-12-10",
    "publisher": "Unknow",
    "cover_state": "bad"
  },
  {
    "id": 391,
    "title": "Dasdsad",
    "author": "Adasdas",
    "publish_date": "2020-01-01",
    "publisher": "Dasdasd",
    "cover_state": "bad"
  },
  {
    "id": 624,
    "title": "Asdas",
    "author": "Aaa Bbb",
    "publish_date": "2000-01-01",
    "publisher": "Sss",
    "cover_state": "regular"
  },
  {
    "id": 504,
    "title": "Aaa",
    "author": "Aaa Bbb",
    "publish_date": "2020-01-01",
    "publisher": "Aaa",
    "cover_state": "good"
  },
  {
    "id": 163,
    "title": "Sss",
    "author": "Xxx Yyy",
    "publish_date": "2020-01-01",
    "publisher": "Ddd",
    "cover_state": "bad"
  },
  {
    "id": 894,
    "title": "Aaa",
    "author": "Aaa Bbb",
    "publish_date": "2020-01-01",
    "publisher": "Aaa",
    "cover_state": "good"
  },
  {
    "id": 285,
    "title": "Asdasd",
    "author": "Aaa Bbb",
    "publish_date": "2000-01-01",
    "publisher": "Sadas",
    "cover_state": "good"
  }
]